odoo10_addon_connector_lengow_teeps-10.0.1.0.0-py2.7-nspkg.pth
odoo/addons/connector_lengow_teeps/README.rst
odoo/addons/connector_lengow_teeps/__init__.py
odoo/addons/connector_lengow_teeps/__manifest__.py
odoo/addons/connector_lengow_teeps/data/lengow_data.xml
odoo/addons/connector_lengow_teeps/models/__init__.py
odoo/addons/connector_lengow_teeps/models/configurator.py
odoo/addons/connector_lengow_teeps/tests/__init__.py
odoo/addons/connector_lengow_teeps/tests/test_lengow_stock.py
odoo10_addon_connector_lengow_teeps-10.0.1.0.0.dist-info/DESCRIPTION.rst
odoo10_addon_connector_lengow_teeps-10.0.1.0.0.dist-info/METADATA
odoo10_addon_connector_lengow_teeps-10.0.1.0.0.dist-info/RECORD
odoo10_addon_connector_lengow_teeps-10.0.1.0.0.dist-info/WHEEL
odoo10_addon_connector_lengow_teeps-10.0.1.0.0.dist-info/metadata.json
odoo10_addon_connector_lengow_teeps-10.0.1.0.0.dist-info/namespace_packages.txt
odoo10_addon_connector_lengow_teeps-10.0.1.0.0.dist-info/top_level.txt
